quantinuum_hugr/__init__.py
quantinuum_hugr/serialization/__init__.py
quantinuum_hugr/serialization/ops.py
quantinuum_hugr/serialization/serial_hugr.py
quantinuum_hugr/serialization/tys.py
quantinuum_hugr-0.1.0a1.dist-info/METADATA
quantinuum_hugr-0.1.0a1.dist-info/WHEEL
quantinuum_hugr-0.1.0a1.dist-info/RECORD
