Metadata-Version: 2.1
Name: quantinuum_hugr
Version: 0.1.0a1
Summary: Quantinuum's common representation for quantum programs
Home-page: https://github.com/CQCL/hugr
License: Apache-2.0
Author: TKET development team
Author-email: tket-support@cambridgequantum.com
Maintainer: TKET development team
Maintainer-email: tket-support@cambridgequantum.com
Requires-Python: >=3.10
Classifier: Environment :: Console
Classifier: Intended Audience :: Developers
Classifier: Intended Audience :: Science/Research
Classifier: License :: OSI Approved :: Apache Software License
Classifier: Operating System :: MacOS :: MacOS X
Classifier: Operating System :: Microsoft :: Windows
Classifier: Operating System :: POSIX :: Linux
Classifier: Programming Language :: Python :: 3
Classifier: Programming Language :: Python :: 3.10
Classifier: Programming Language :: Python :: 3.11
Classifier: Programming Language :: Python :: 3.12
Classifier: Topic :: Scientific/Engineering
Requires-Dist: pydantic (>=2.6.4,<3.0.0)
Project-URL: Repository, https://github.com/CQCL/hugr
